Workbook

Sheet 00_Supuestos
A1: Supuestos clave (editar celdas azules)
A3: TRM USD/COP | B3: 3800
A4: Moneda base del archivo | B4: COP
A6: Notas
A7: 1) Si una línea está en USD, el modelo la convierte a COP usando la TRM.
A8: 2) Ajusta Mes Inicio / Mes Fin según el cronograma real.

Sheet 01_Presupuesto
A1: Rubro | B1: Subrubro | C1: Actividad (del plan) | D1: Fuente (Mes/Workstream) | E1: Responsable | F1: Tipo costo | G1: Driver/Unidad | H1: Qty por mes | I1: Costo unitario | J1: Moneda | K1: TRM | L1: Mes inicio | M1: Mes fin | N1: Notas/Supuestos | O1: Feb-26 | P1: Mar-26 | Q1: Apr-26 | R1: May-26 | S1: Jun-26 | T1: Jul-26 | U1: Aug-26 | V1: Sep-26 | W1: Oct-26 | X1: Nov-26 | Y1: Dec-26 | Z1: Jan-27 | AA1: Total Año (COP)
O2: 46054 | P2: 46082 | Q2: 46113 | R2: 46143 | S2: 46174 | T2: 46204 | U2: 46235 | V2: 46266 | W2: 46296 | X2: 46327 | Y2: 46357 | Z2: 46388
A3: Estrategia/Producto | B3: Material comercial | C3: Elaboracion de la Guía “Invierte en Panamá con tranquilidad” (versión Bogotá): pasos, tiempos, documentos, pagos, FAQs | D3: Mes 1 | E3: Dir. Bogotá + Agencia | F3: One-off | G3: Guía | H3: 1 | I3: 5000 | J3: USD | K3: ='00_Supuestos'!$B$3 -> 3800 | L3: 46054 | M3: 46054 | N3: Documento base para apertura. Ver Mes 1. | O3: =IF(AND($L3<=O$2,$M3>=O$2),$H3*$I3*IF($J3="USD",$K3,1),0) -> 19000000 | P3: =IF(AND($L3<=P$2,$M3>=P$2),$H3*$I3*IF($J3="USD",$K3,1),0) -> 0 | Q3: =IF(AND($L3<=Q$2,$M3>=Q$2),$H3*$I3*IF($J3="USD",$K3,1),0) -> 0 | R3: =IF(AND($L3<=R$2,$M3>=R$2),$H3*$I3*IF($J3="USD",$K3,1),0) -> 0 | S3: =IF(AND($L3<=S$2,$M3>=S$2),$H3*$I3*IF($J3="USD",$K3,1),0) -> 0 | T3: =IF(AND($L3<=T$2,$M3>=T$2),$H3*$I3*IF($J3="USD",$K3,1),0) -> 0 | U3: =IF(AND($L3<=U$2,$M3>=U$2),$H3*$I3*IF($J3="USD",$K3,1),0) -> 0 | V3: =IF(AND($L3<=V$2,$M3>=V$2),$H3*$I3*IF($J3="USD",$K3,1),0) -> 0 | ... Z3: =IF(AND($L3<=Z$2,$M3>=Z$2),$H3*$I3*IF($J3="USD",$K3,1),0) -> 0 | AA3: =SUM(O3:Z3) -> 19000000
A4: Ventas & CRM | B4: Herramientas | C4: CRM + etapas + SLA (licencia + configuración) | D4: Mes 1 / Workstream C | E4: Dir. Bogotá + Soporte de IT local + IT Panama | F4: Fijo | G4: Mes | H4: 1 | I4: 300 | J4: USD | K4: ='00_Supuestos'!$B$3 -> 3800 | L4: 46054 | M4: 46388 | N4: Licencia mensual + implementación inicial. | O4: =IF(AND($L4<=O$2,$M4>=O$2),$H4*$I4*IF($J4="USD",$K4,1),0) -> 1140000 | P4: =IF(AND($L4<=P$2,$M4>=P$2),$H4*$I4*IF($J4="USD",$K4,1),0) -> 1140000 | Q4: =IF(AND($L4<=Q$2,$M4>=Q$2),$H4*$I4*IF($J4="USD",$K4,1),0) -> 1140000 | R4: =IF(AND($L4<=R$2,$M4>=R$2),$H4*$I4*IF($J4="USD",$K4,1),0) -> 1140000 | S4: =IF(AND($L4<=S$2,$M4>=S$2),$H4*$I4*IF($J4="USD",$K4,1),0) -> 1140000 | T4: =IF(AND($L4<=T$2,$M4>=T$2),$H4*$I4*IF($J4="USD",$K4,1),0) -> 1140000 | U4: =IF(AND($L4<=U$2,$M4>=U$2),$H4*$I4*IF($J4="USD",$K4,1),0) -> 1140000 | V4: =IF(AND($L4<=V$2,$M4>=V$2),$H4*$I4*IF($J4="USD",$K4,1),0) -> 1140000 | ... Z4: =IF(AND($L4<=Z$2,$M4>=Z$2),$H4*$I4*IF($J4="USD",$K4,1),0) -> 1140000 | AA4: =SUM(O4:Z4) -> 13680000
A5: Ventas & CRM | B5: Entrenamiento | C5: Entrenamiento semanal (equipo comercial) | D5: Workstream C | E5: Comercial | F5: Fijo | G5: Mes | H5: 1 | I5: 100 | J5: USD | K5: ='00_Supuestos'!$B$3 -> 3800 | L5: 46054 | M5: 46388 | N5: Sesiones internas o coach externo. | O5: =IF(AND($L5<=O$2,$M5>=O$2),$H5*$I5*IF($J5="USD",$K5,1),0) -> 380000 | P5: =IF(AND($L5<=P$2,$M5>=P$2),$H5*$I5*IF($J5="USD",$K5,1),0) -> 380000 | Q5: =IF(AND($L5<=Q$2,$M5>=Q$2),$H5*$I5*IF($J5="USD",$K5,1),0) -> 380000 | R5: =IF(AND($L5<=R$2,$M5>=R$2),$H5*$I5*IF($J5="USD",$K5,1),0) -> 380000 | S5: =IF(AND($L5<=S$2,$M5>=S$2),$H5*$I5*IF($J5="USD",$K5,1),0) -> 380000 | T5: =IF(AND($L5<=T$2,$M5>=T$2),$H5*$I5*IF($J5="USD",$K5,1),0) -> 380000 | U5: =IF(AND($L5<=U$2,$M5>=U$2),$H5*$I5*IF($J5="USD",$K5,1),0) -> 380000 | V5: =IF(AND($L5<=V$2,$M5>=V$2),$H5*$I5*IF($J5="USD",$K5,1),0) -> 380000 | ... Z5: =IF(AND($L5<=Z$2,$M5>=Z$2),$H5*$I5*IF($J5="USD",$K5,1),0) -> 380000 | AA5: =SUM(O5:Z5) -> 4560000
A6: Marketing Digital | B6: Pauta | C6: Campañas por segmento (performance), proveedores de Infraestructura | D6: Mes 2 / Workstream B | E6: Dir. Bogotá + MKt | F6: Variable | G6: Mes | H6: 1 | I6: 1000 | J6: USD | K6: ='00_Supuestos'!$B$3 -> 3800 | L6: 46054 | M6: 46388 | N6: Para mantener presencia de marca validar mensajes/segmentos. | O6: =IF(AND($L6<=O$2,$M6>=O$2),$H6*$I6*IF($J6="USD",$K6,1),0) -> 3800000 | P6: =IF(AND($L6<=P$2,$M6>=P$2),$H6*$I6*IF($J6="USD",$K6,1),0) -> 3800000 | Q6: =IF(AND($L6<=Q$2,$M6>=Q$2),$H6*$I6*IF($J6="USD",$K6,1),0) -> 3800000 | R6: =IF(AND($L6<=R$2,$M6>=R$2),$H6*$I6*IF($J6="USD",$K6,1),0) -> 3800000 | S6: =IF(AND($L6<=S$2,$M6>=S$2),$H6*$I6*IF($J6="USD",$K6,1),0) -> 3800000 | T6: =IF(AND($L6<=T$2,$M6>=T$2),$H6*$I6*IF($J6="USD",$K6,1),0) -> 3800000 | U6: =IF(AND($L6<=U$2,$M6>=U$2),$H6*$I6*IF($J6="USD",$K6,1),0) -> 3800000 | V6: =IF(AND($L6<=V$2,$M6>=V$2),$H6*$I6*IF($J6="USD",$K6,1),0) -> 3800000 | ... Z6: =IF(AND($L6<=Z$2,$M6>=Z$2),$H6*$I6*IF($J6="USD",$K6,1),0) -> 3800000 | AA6: =SUM(O6:Z6) -> 45600000
A7: Alianzas | B7: Programa aliados | C7: Activación de alianzas: wealth managers, firmas contables/tributarias, abogados patrimoniales, gremios, banca FX | D7: Mes 3 | E7: Dir. Bogotá | F7: Fijo | G7: Mes | H7: 1 | I7: 400 | J7: USD | K7: ='00_Supuestos'!$B$3 -> 3800 | L7: 46113 | M7: 46388 | N7: Reuniones, materiales, seguimiento, posibles patrocinios. | O7: =IF(AND($L7<=O$2,$M7>=O$2),$H7*$I7*IF($J7="USD",$K7,1),0) -> 0 | P7: =IF(AND($L7<=P$2,$M7>=P$2),$H7*$I7*IF($J7="USD",$K7,1),0) -> 0 | Q7: =IF(AND($L7<=Q$2,$M7>=Q$2),$H7*$I7*IF($J7="USD",$K7,1),0) -> 1520000 | R7: =IF(AND($L7<=R$2,$M7>=R$2),$H7*$I7*IF($J7="USD",$K7,1),0) -> 1520000 | S7: =IF(AND($L7<=S$2,$M7>=S$2),$H7*$I7*IF($J7="USD",$K7,1),0) -> 1520000 | T7: =IF(AND($L7<=T$2,$M7>=T$2),$H7*$I7*IF($J7="USD",$K7,1),0) -> 1520000 | U7: =IF(AND($L7<=U$2,$M7>=U$2),$H7*$I7*IF($J7="USD",$K7,1),0) -> 1520000 | V7: =IF(AND($L7<=V$2,$M7>=V$2),$H7*$I7*IF($J7="USD",$K7,1),0) -> 1520000 | ... Z7: =IF(AND($L7<=Z$2,$M7>=Z$2),$H7*$I7*IF($J7="USD",$K7,1),0) -> 1520000 | AA7: =SUM(O7:Z7) -> 15200000
A8: Marketing Digital | B8: Contenido | C8: Comunity Manager para Calendario de contenidos + producción (video corto, testimonios, comparativos, agencia performance, creador audiovisual, copy) | D8: Mes 3 / Workstream B | E8: WCM | F8: Fijo | G8: Mes | H8: 1 | I8: 2000 | J8: USD | K8: ='00_Supuestos'!$B$3 -> 3800 | L8: 46054 | M8: 46388 | N8: Producción mensual + edición. | O8: =IF(AND($L8<=O$2,$M8>=O$2),$H8*$I8*IF($J8="USD",$K8,1),0) -> 7600000 | P8: =IF(AND($L8<=P$2,$M8>=P$2),$H8*$I8*IF($J8="USD",$K8,1),0) -> 7600000 | Q8: =IF(AND($L8<=Q$2,$M8>=Q$2),$H8*$I8*IF($J8="USD",$K8,1),0) -> 7600000 | R8: =IF(AND($L8<=R$2,$M8>=R$2),$H8*$I8*IF($J8="USD",$K8,1),0) -> 7600000 | S8: =IF(AND($L8<=S$2,$M8>=S$2),$H8*$I8*IF($J8="USD",$K8,1),0) -> 7600000 | T8: =IF(AND($L8<=T$2,$M8>=T$2),$H8*$I8*IF($J8="USD",$K8,1),0) -> 7600000 | U8: =IF(AND($L8<=U$2,$M8>=U$2),$H8*$I8*IF($J8="USD",$K8,1),0) -> 7600000 | V8: =IF(AND($L8<=V$2,$M8>=V$2),$H8*$I8*IF($J8="USD",$K8,1),0) -> 7600000 | ... Z8: =IF(AND($L8<=Z$2,$M8>=Z$2),$H8*$I8*IF($J8="USD",$K8,1),0) -> 7600000 | AA8: =SUM(O8:Z8) -> 91200000
A9: Estrategia/Producto | B9: Paquetes | C9: “Kit Inversionista Bogotá” (checklist, timeline, costos, riesgos) + 3 rutas (Esencial/Patrimonial/Family Office) + simuladores simples | D9: Mes 6 / Workstream A,G | E9: Mkt+Legal | F9: One-off | G9: Paquete | H9: 1 | I9: 1000 | J9: USD | K9: ='00_Supuestos'!$B$3 -> 3800 | L9: 46054 | M9: 46082 | N9: Incluye diseño, revisión legal y tributaria. | O9: =IF(AND($L9<=O$2,$M9>=O$2),$H9*$I9*IF($J9="USD",$K9,1),0) -> 3800000 | P9: =IF(AND($L9<=P$2,$M9>=P$2),$H9*$I9*IF($J9="USD",$K9,1),0) -> 3800000 | Q9: =IF(AND($L9<=Q$2,$M9>=Q$2),$H9*$I9*IF($J9="USD",$K9,1),0) -> 0 | R9: =IF(AND($L9<=R$2,$M9>=R$2),$H9*$I9*IF($J9="USD",$K9,1),0) -> 0 | S9: =IF(AND($L9<=S$2,$M9>=S$2),$H9*$I9*IF($J9="USD",$K9,1),0) -> 0 | T9: =IF(AND($L9<=T$2,$M9>=T$2),$H9*$I9*IF($J9="USD",$K9,1),0) -> 0 | U9: =IF(AND($L9<=U$2,$M9>=U$2),$H9*$I9*IF($J9="USD",$K9,1),0) -> 0 | V9: =IF(AND($L9<=V$2,$M9>=V$2),$H9*$I9*IF($J9="USD",$K9,1),0) -> 0 | ... Z9: =IF(AND($L9<=Z$2,$M9>=Z$2),$H9*$I9*IF($J9="USD",$K9,1),0) -> 0 | AA9: =SUM(O9:Z9) -> 7600000
A10: Eventos & PR | B10: Eventos recurrentes | C10: Eventos focalizados (4 eventos/mes Mar–Dic) | D10: Workstream D | E10: Dir. Bogotá | F10: Variable | G10: Evento | H10: 1 | I10: 2500 | J10: USD | K10: ='00_Supuestos'!$B$3 -> 3800 | L10: 46082 | M10: 46388 | N10: Ejecutar mensualmente. Ajusta # eventos y costo/evento. | O10: =IF(AND($L10<=O$2,$M10>=O$2),$H10*$I10*IF($J10="USD",$K10,1),0) -> 0 | P10: =IF(AND($L10<=P$2,$M10>=P$2),$H10*$I10*IF($J10="USD",$K10,1),0) -> 9500000 | Q10: =IF(AND($L10<=Q$2,$M10>=Q$2),$H10*$I10*IF($J10="USD",$K10,1),0) -> 9500000 | R10: =IF(AND($L10<=R$2,$M10>=R$2),$H10*$I10*IF($J10="USD",$K10,1),0) -> 9500000 | S10: =IF(AND($L10<=S$2,$M10>=S$2),$H10*$I10*IF($J10="USD",$K10,1),0) -> 9500000 | T10: =IF(AND($L10<=T$2,$M10>=T$2),$H10*$I10*IF($J10="USD",$K10,1),0) -> 9500000 | U10: =IF(AND($L10<=U$2,$M10>=U$2),$H10*$I10*IF($J10="USD",$K10,1),0) -> 9500000 | V10: =IF(AND($L10<=V$2,$M10>=V$2),$H10*$I10*IF($J10="USD",$K10,1),0) -> 9500000 | ... Z10: =IF(AND($L10<=Z$2,$M10>=Z$2),$H10*$I10*IF($J10="USD",$K10,1),0) -> 9500000 | AA10: =SUM(O10:Z10) -> 104500000
A11: Eventos & PR | B11: Eventos recurrentes | C11: TOUR CLIENTES POTENCIALES | D11: Workstream D | E11: Dir. Bogotá | F11: Variable | G11: Evento | H11: 1 | I11: =1000*0 -> 0 | J11: USD | K11: ='00_Supuestos'!$B$3 -> 3800 | L11: 46082 | M11: 46357 | N11: Ejecutar mensualmente. Ajusta # Asistente, viajes y alcance | O11: =IF(AND($L11<=O$2,$M11>=O$2),$H11*$I11*IF($J11="USD",$K11,1),0) -> 0 | P11: =IF(AND($L11<=P$2,$M11>=P$2),$H11*$I11*IF($J11="USD",$K11,1),0) -> 0 | R11: =IF(AND($L11<=R$2,$M11>=R$2),$H11*$I11*IF($J11="USD",$K11,1),0) -> 0 | V11: =IF(AND($L11<=V$2,$M11>=V$2),$H11*$I11*IF($J11="USD",$K11,1),0) -> 0 | X11: =IF(AND($L11<=X$2,$M11>=X$2),$H11*$I11*IF($J11="USD",$K11,1),0) -> 0 | Z11: =IF(AND($L11<=Z$2,$M11>=Z$2),$H11*$I11*IF($J11="USD",$K11,1),0) -> 0 | AA11: =SUM(O11:Z11) -> 0
A12: Marketing Digital | B12: Influencers | C12: Micro-influencers (finanzas/real estate) + contenido educativo | D12: Mes 9 | E12: Mkt | F12: One-off | G12: Campaña | H12: 1 | I12: 500 | J12: USD | K12: ='00_Supuestos'!$B$3 -> 3800 | L12: 46054 | M12: 46388 | N12: Pago + producción; elegir por credibilidad. | O12: =IF(AND($L12<=O$2,$M12>=O$2),$H12*$I12*IF($J12="USD",$K12,1),0) -> 1900000 | P12: =IF(AND($L12<=P$2,$M12>=P$2),$H12*$I12*IF($J12="USD",$K12,1),0) -> 1900000 | Q12: =IF(AND($L12<=Q$2,$M12>=Q$2),$H12*$I12*IF($J12="USD",$K12,1),0) -> 1900000 | R12: =IF(AND($L12<=R$2,$M12>=R$2),$H12*$I12*IF($J12="USD",$K12,1),0) -> 1900000 | S12: =IF(AND($L12<=S$2,$M12>=S$2),$H12*$I12*IF($J12="USD",$K12,1),0) -> 1900000 | T12: =IF(AND($L12<=T$2,$M12>=T$2),$H12*$I12*IF($J12="USD",$K12,1),0) -> 1900000 | U12: =IF(AND($L12<=U$2,$M12>=U$2),$H12*$I12*IF($J12="USD",$K12,1),0) -> 1900000 | V12: =IF(AND($L12<=V$2,$M12>=V$2),$H12*$I12*IF($J12="USD",$K12,1),0) -> 1900000 | ... Z12: =IF(AND($L12<=Z$2,$M12>=Z$2),$H12*$I12*IF($J12="USD",$K12,1),0) -> 1900000 | AA12: =SUM(O12:Z12) -> 22800000
A13: Operación | B13: Equipo | C13: Direccion comercial (director comercial, inside sales, closers, soporte) | D13: Workstream C (Actores) | E13: RRHH | F13: Fijo | G13: Mes | H13: 1 | I13: 4000 | J13: USD | K13: ='00_Supuestos'!$B$3 -> 3800 | L13: 46054 | M13: 46388 | N13: Nómina + prestaciones + comisiones (si se incluyen aquí). | O13: =IF(AND($L13<=O$2,$M13>=O$2),$H13*$I13*IF($J13="USD",$K13,1),0) -> 15200000 | P13: =IF(AND($L13<=P$2,$M13>=P$2),$H13*$I13*IF($J13="USD",$K13,1),0) -> 15200000 | Q13: =IF(AND($L13<=Q$2,$M13>=Q$2),$H13*$I13*IF($J13="USD",$K13,1),0) -> 15200000 | R13: =IF(AND($L13<=R$2,$M13>=R$2),$H13*$I13*IF($J13="USD",$K13,1),0) -> 15200000 | S13: =IF(AND($L13<=S$2,$M13>=S$2),$H13*$I13*IF($J13="USD",$K13,1),0) -> 15200000 | T13: =IF(AND($L13<=T$2,$M13>=T$2),$H13*$I13*IF($J13="USD",$K13,1),0) -> 15200000 | U13: =IF(AND($L13<=U$2,$M13>=U$2),$H13*$I13*IF($J13="USD",$K13,1),0) -> 15200000 | V13: =IF(AND($L13<=V$2,$M13>=V$2),$H13*$I13*IF($J13="USD",$K13,1),0) -> 15200000 | ... Z13: =IF(AND($L13<=Z$2,$M13>=Z$2),$H13*$I13*IF($J13="USD",$K13,1),0) -> 15200000 | AA13: =SUM(O13:Z13) -> 182400000
AA15: =SUM(AA3:AA14) -> 506540000
AA16: =+AA15/3800 -> 133300

Sheet 02_Resumen
A1: Resumen por rubro y por mes (COP)
A3: Rubro | B3: Feb-26 | C3: Mar-26 | D3: Apr-26 | E3: May-26 | F3: Jun-26 | G3: Jul-26 | H3: Aug-26 | I3: Sep-26 | J3: Oct-26 | K3: Nov-26 | L3: Dec-26 | M3: Jan-27 | N3: Total Año
A4: Alianzas | B4: =SUMIF('01_Presupuesto'!$A$3:$A$13,$A4,'01_Presupuesto'!$O$3:$O$13) -> 0 | C4: =SUMIF('01_Presupuesto'!$A$3:$A$13,$A4,'01_Presupuesto'!$P$3:$P$13) -> 0 | D4: =SUMIF('01_Presupuesto'!$A$3:$A$13,$A4,'01_Presupuesto'!$Q$3:$Q$13) -> 1520000 | E4: =SUMIF('01_Presupuesto'!$A$3:$A$13,$A4,'01_Presupuesto'!$R$3:$R$13) -> 1520000 | F4: =SUMIF('01_Presupuesto'!$A$3:$A$13,$A4,'01_Presupuesto'!$S$3:$S$13) -> 1520000 | G4: =SUMIF('01_Presupuesto'!$A$3:$A$13,$A4,'01_Presupuesto'!$T$3:$T$13) -> 1520000 | H4: =SUMIF('01_Presupuesto'!$A$3:$A$13,$A4,'01_Presupuesto'!$U$3:$U$13) -> 1520000 | I4: =SUMIF('01_Presupuesto'!$A$3:$A$13,$A4,'01_Presupuesto'!$V$3:$V$13) -> 1520000 | J4: =SUMIF('01_Presupuesto'!$A$3:$A$13,$A4,'01_Presupuesto'!$W$3:$W$13) -> 1520000 | K4: =SUMIF('01_Presupuesto'!$A$3:$A$13,$A4,'01_Presupuesto'!$X$3:$X$13) -> 1520000 | L4: =SUMIF('01_Presupuesto'!$A$3:$A$13,$A4,'01_Presupuesto'!$Y$3:$Y$13) -> 1520000 | M4: =SUMIF('01_Presupuesto'!$A$3:$A$13,$A4,'01_Presupuesto'!$Z$3:$Z$13) -> 1520000 | N4: =SUM(B4:M4) -> 15200000
A5: Estrategia/Producto | B5: =SUMIF('01_Presupuesto'!$A$3:$A$13,$A5,'01_Presupuesto'!$O$3:$O$13) -> 22800000 | C5: =SUMIF('01_Presupuesto'!$A$3:$A$13,$A5,'01_Presupuesto'!$P$3:$P$13) -> 3800000 | D5: =SUMIF('01_Presupuesto'!$A$3:$A$13,$A5,'01_Presupuesto'!$Q$3:$Q$13) -> 0 | E5: =SUMIF('01_Presupuesto'!$A$3:$A$13,$A5,'01_Presupuesto'!$R$3:$R$13) -> 0 | F5: =SUMIF('01_Presupuesto'!$A$3:$A$13,$A5,'01_Presupuesto'!$S$3:$S$13) -> 0 | G5: =SUMIF('01_Presupuesto'!$A$3:$A$13,$A5,'01_Presupuesto'!$T$3:$T$13) -> 0 | H5: =SUMIF('01_Presupuesto'!$A$3:$A$13,$A5,'01_Presupuesto'!$U$3:$U$13) -> 0 | I5: =SUMIF('01_Presupuesto'!$A$3:$A$13,$A5,'01_Presupuesto'!$V$3:$V$13) -> 0 | J5: =SUMIF('01_Presupuesto'!$A$3:$A$13,$A5,'01_Presupuesto'!$W$3:$W$13) -> 0 | K5: =SUMIF('01_Presupuesto'!$A$3:$A$13,$A5,'01_Presupuesto'!$X$3:$X$13) -> 0 | L5: =SUMIF('01_Presupuesto'!$A$3:$A$13,$A5,'01_Presupuesto'!$Y$3:$Y$13) -> 0 | M5: =SUMIF('01_Presupuesto'!$A$3:$A$13,$A5,'01_Presupuesto'!$Z$3:$Z$13) -> 0 | N5: =SUM(B5:M5) -> 26600000
A6: Eventos & PR | B6: =SUMIF('01_Presupuesto'!$A$3:$A$13,$A6,'01_Presupuesto'!$O$3:$O$13) -> 0 | C6: =SUMIF('01_Presupuesto'!$A$3:$A$13,$A6,'01_Presupuesto'!$P$3:$P$13) -> 9500000 | D6: =SUMIF('01_Presupuesto'!$A$3:$A$13,$A6,'01_Presupuesto'!$Q$3:$Q$13) -> 9500000 | E6: =SUMIF('01_Presupuesto'!$A$3:$A$13,$A6,'01_Presupuesto'!$R$3:$R$13) -> 9500000 | F6: =SUMIF('01_Presupuesto'!$A$3:$A$13,$A6,'01_Presupuesto'!$S$3:$S$13) -> 9500000 | G6: =SUMIF('01_Presupuesto'!$A$3:$A$13,$A6,'01_Presupuesto'!$T$3:$T$13) -> 9500000 | H6: =SUMIF('01_Presupuesto'!$A$3:$A$13,$A6,'01_Presupuesto'!$U$3:$U$13) -> 9500000 | I6: =SUMIF('01_Presupuesto'!$A$3:$A$13,$A6,'01_Presupuesto'!$V$3:$V$13) -> 9500000 | J6: =SUMIF('01_Presupuesto'!$A$3:$A$13,$A6,'01_Presupuesto'!$W$3:$W$13) -> 9500000 | K6: =SUMIF('01_Presupuesto'!$A$3:$A$13,$A6,'01_Presupuesto'!$X$3:$X$13) -> 9500000 | L6: =SUMIF('01_Presupuesto'!$A$3:$A$13,$A6,'01_Presupuesto'!$Y$3:$Y$13) -> 9500000 | M6: =SUMIF('01_Presupuesto'!$A$3:$A$13,$A6,'01_Presupuesto'!$Z$3:$Z$13) -> 9500000 | N6: =SUM(B6:M6) -> 104500000
A7: Gestión & Control | B7: =SUMIF('01_Presupuesto'!$A$3:$A$13,$A7,'01_Presupuesto'!$O$3:$O$13) -> 0 | C7: =SUMIF('01_Presupuesto'!$A$3:$A$13,$A7,'01_Presupuesto'!$P$3:$P$13) -> 0 | D7: =SUMIF('01_Presupuesto'!$A$3:$A$13,$A7,'01_Presupuesto'!$Q$3:$Q$13) -> 0 | E7: =SUMIF('01_Presupuesto'!$A$3:$A$13,$A7,'01_Presupuesto'!$R$3:$R$13) -> 0 | F7: =SUMIF('01_Presupuesto'!$A$3:$A$13,$A7,'01_Presupuesto'!$S$3:$S$13) -> 0 | G7: =SUMIF('01_Presupuesto'!$A$3:$A$13,$A7,'01_Presupuesto'!$T$3:$T$13) -> 0 | H7: =SUMIF('01_Presupuesto'!$A$3:$A$13,$A7,'01_Presupuesto'!$U$3:$U$13) -> 0 | I7: =SUMIF('01_Presupuesto'!$A$3:$A$13,$A7,'01_Presupuesto'!$V$3:$V$13) -> 0 | J7: =SUMIF('01_Presupuesto'!$A$3:$A$13,$A7,'01_Presupuesto'!$W$3:$W$13) -> 0 | K7: =SUMIF('01_Presupuesto'!$A$3:$A$13,$A7,'01_Presupuesto'!$X$3:$X$13) -> 0 | L7: =SUMIF('01_Presupuesto'!$A$3:$A$13,$A7,'01_Presupuesto'!$Y$3:$Y$13) -> 0 | M7: =SUMIF('01_Presupuesto'!$A$3:$A$13,$A7,'01_Presupuesto'!$Z$3:$Z$13) -> 0 | N7: =SUM(B7:M7) -> 0
A8: Legal/Compliance & FX | B8: =SUMIF('01_Presupuesto'!$A$3:$A$13,$A8,'01_Presupuesto'!$O$3:$O$13) -> 0 | C8: =SUMIF('01_Presupuesto'!$A$3:$A$13,$A8,'01_Presupuesto'!$P$3:$P$13) -> 0 | D8: =SUMIF('01_Presupuesto'!$A$3:$A$13,$A8,'01_Presupuesto'!$Q$3:$Q$13) -> 0 | E8: =SUMIF('01_Presupuesto'!$A$3:$A$13,$A8,'01_Presupuesto'!$R$3:$R$13) -> 0 | F8: =SUMIF('01_Presupuesto'!$A$3:$A$13,$A8,'01_Presupuesto'!$S$3:$S$13) -> 0 | G8: =SUMIF('01_Presupuesto'!$A$3:$A$13,$A8,'01_Presupuesto'!$T$3:$T$13) -> 0 | H8: =SUMIF('01_Presupuesto'!$A$3:$A$13,$A8,'01_Presupuesto'!$U$3:$U$13) -> 0 | I8: =SUMIF('01_Presupuesto'!$A$3:$A$13,$A8,'01_Presupuesto'!$V$3:$V$13) -> 0 | J8: =SUMIF('01_Presupuesto'!$A$3:$A$13,$A8,'01_Presupuesto'!$W$3:$W$13) -> 0 | K8: =SUMIF('01_Presupuesto'!$A$3:$A$13,$A8,'01_Presupuesto'!$X$3:$X$13) -> 0 | L8: =SUMIF('01_Presupuesto'!$A$3:$A$13,$A8,'01_Presupuesto'!$Y$3:$Y$13) -> 0 | M8: =SUMIF('01_Presupuesto'!$A$3:$A$13,$A8,'01_Presupuesto'!$Z$3:$Z$13) -> 0 | N8: =SUM(B8:M8) -> 0
A9: Marca/Presencia | B9: =SUMIF('01_Presupuesto'!$A$3:$A$13,$A9,'01_Presupuesto'!$O$3:$O$13) -> 0 | C9: =SUMIF('01_Presupuesto'!$A$3:$A$13,$A9,'01_Presupuesto'!$P$3:$P$13) -> 0 | D9: =SUMIF('01_Presupuesto'!$A$3:$A$13,$A9,'01_Presupuesto'!$Q$3:$Q$13) -> 0 | E9: =SUMIF('01_Presupuesto'!$A$3:$A$13,$A9,'01_Presupuesto'!$R$3:$R$13) -> 0 | F9: =SUMIF('01_Presupuesto'!$A$3:$A$13,$A9,'01_Presupuesto'!$S$3:$S$13) -> 0 | G9: =SUMIF('01_Presupuesto'!$A$3:$A$13,$A9,'01_Presupuesto'!$T$3:$T$13) -> 0 | H9: =SUMIF('01_Presupuesto'!$A$3:$A$13,$A9,'01_Presupuesto'!$U$3:$U$13) -> 0 | I9: =SUMIF('01_Presupuesto'!$A$3:$A$13,$A9,'01_Presupuesto'!$V$3:$V$13) -> 0 | J9: =SUMIF('01_Presupuesto'!$A$3:$A$13,$A9,'01_Presupuesto'!$W$3:$W$13) -> 0 | K9: =SUMIF('01_Presupuesto'!$A$3:$A$13,$A9,'01_Presupuesto'!$X$3:$X$13) -> 0 | L9: =SUMIF('01_Presupuesto'!$A$3:$A$13,$A9,'01_Presupuesto'!$Y$3:$Y$13) -> 0 | M9: =SUMIF('01_Presupuesto'!$A$3:$A$13,$A9,'01_Presupuesto'!$Z$3:$Z$13) -> 0 | N9: =SUM(B9:M9) -> 0
A10: Marketing Digital | B10: =SUMIF('01_Presupuesto'!$A$3:$A$13,$A10,'01_Presupuesto'!$O$3:$O$13) -> 13300000 | C10: =SUMIF('01_Presupuesto'!$A$3:$A$13,$A10,'01_Presupuesto'!$P$3:$P$13) -> 13300000 | D10: =SUMIF('01_Presupuesto'!$A$3:$A$13,$A10,'01_Presupuesto'!$Q$3:$Q$13) -> 13300000 | E10: =SUMIF('01_Presupuesto'!$A$3:$A$13,$A10,'01_Presupuesto'!$R$3:$R$13) -> 13300000 | F10: =SUMIF('01_Presupuesto'!$A$3:$A$13,$A10,'01_Presupuesto'!$S$3:$S$13) -> 13300000 | G10: =SUMIF('01_Presupuesto'!$A$3:$A$13,$A10,'01_Presupuesto'!$T$3:$T$13) -> 13300000 | H10: =SUMIF('01_Presupuesto'!$A$3:$A$13,$A10,'01_Presupuesto'!$U$3:$U$13) -> 13300000 | I10: =SUMIF('01_Presupuesto'!$A$3:$A$13,$A10,'01_Presupuesto'!$V$3:$V$13) -> 13300000 | J10: =SUMIF('01_Presupuesto'!$A$3:$A$13,$A10,'01_Presupuesto'!$W$3:$W$13) -> 13300000 | K10: =SUMIF('01_Presupuesto'!$A$3:$A$13,$A10,'01_Presupuesto'!$X$3:$X$13) -> 13300000 | L10: =SUMIF('01_Presupuesto'!$A$3:$A$13,$A10,'01_Presupuesto'!$Y$3:$Y$13) -> 13300000 | M10: =SUMIF('01_Presupuesto'!$A$3:$A$13,$A10,'01_Presupuesto'!$Z$3:$Z$13) -> 13300000 | N10: =SUM(B10:M10) -> 159600000
A11: Operación | B11: =SUMIF('01_Presupuesto'!$A$3:$A$13,$A11,'01_Presupuesto'!$O$3:$O$13) -> 15200000 | C11: =SUMIF('01_Presupuesto'!$A$3:$A$13,$A11,'01_Presupuesto'!$P$3:$P$13) -> 15200000 | D11: =SUMIF('01_Presupuesto'!$A$3:$A$13,$A11,'01_Presupuesto'!$Q$3:$Q$13) -> 15200000 | E11: =SUMIF('01_Presupuesto'!$A$3:$A$13,$A11,'01_Presupuesto'!$R$3:$R$13) -> 15200000 | F11: =SUMIF('01_Presupuesto'!$A$3:$A$13,$A11,'01_Presupuesto'!$S$3:$S$13) -> 15200000 | G11: =SUMIF('01_Presupuesto'!$A$3:$A$13,$A11,'01_Presupuesto'!$T$3:$T$13) -> 15200000 | H11: =SUMIF('01_Presupuesto'!$A$3:$A$13,$A11,'01_Presupuesto'!$U$3:$U$13) -> 15200000 | I11: =SUMIF('01_Presupuesto'!$A$3:$A$13,$A11,'01_Presupuesto'!$V$3:$V$13) -> 15200000 | J11: =SUMIF('01_Presupuesto'!$A$3:$A$13,$A11,'01_Presupuesto'!$W$3:$W$13) -> 15200000 | K11: =SUMIF('01_Presupuesto'!$A$3:$A$13,$A11,'01_Presupuesto'!$X$3:$X$13) -> 15200000 | L11: =SUMIF('01_Presupuesto'!$A$3:$A$13,$A11,'01_Presupuesto'!$Y$3:$Y$13) -> 15200000 | M11: =SUMIF('01_Presupuesto'!$A$3:$A$13,$A11,'01_Presupuesto'!$Z$3:$Z$13) -> 15200000 | N11: =SUM(B11:M11) -> 182400000
A12: Postventa & Comunidad | B12: =SUMIF('01_Presupuesto'!$A$3:$A$13,$A12,'01_Presupuesto'!$O$3:$O$13) -> 0 | C12: =SUMIF('01_Presupuesto'!$A$3:$A$13,$A12,'01_Presupuesto'!$P$3:$P$13) -> 0 | D12: =SUMIF('01_Presupuesto'!$A$3:$A$13,$A12,'01_Presupuesto'!$Q$3:$Q$13) -> 0 | E12: =SUMIF('01_Presupuesto'!$A$3:$A$13,$A12,'01_Presupuesto'!$R$3:$R$13) -> 0 | F12: =SUMIF('01_Presupuesto'!$A$3:$A$13,$A12,'01_Presupuesto'!$S$3:$S$13) -> 0 | G12: =SUMIF('01_Presupuesto'!$A$3:$A$13,$A12,'01_Presupuesto'!$T$3:$T$13) -> 0 | H12: =SUMIF('01_Presupuesto'!$A$3:$A$13,$A12,'01_Presupuesto'!$U$3:$U$13) -> 0 | I12: =SUMIF('01_Presupuesto'!$A$3:$A$13,$A12,'01_Presupuesto'!$V$3:$V$13) -> 0 | J12: =SUMIF('01_Presupuesto'!$A$3:$A$13,$A12,'01_Presupuesto'!$W$3:$W$13) -> 0 | K12: =SUMIF('01_Presupuesto'!$A$3:$A$13,$A12,'01_Presupuesto'!$X$3:$X$13) -> 0 | L12: =SUMIF('01_Presupuesto'!$A$3:$A$13,$A12,'01_Presupuesto'!$Y$3:$Y$13) -> 0 | M12: =SUMIF('01_Presupuesto'!$A$3:$A$13,$A12,'01_Presupuesto'!$Z$3:$Z$13) -> 0 | N12: =SUM(B12:M12) -> 0
A13: Ventas & CRM | B13: =SUMIF('01_Presupuesto'!$A$3:$A$13,$A13,'01_Presupuesto'!$O$3:$O$13) -> 1520000 | C13: =SUMIF('01_Presupuesto'!$A$3:$A$13,$A13,'01_Presupuesto'!$P$3:$P$13) -> 1520000 | D13: =SUMIF('01_Presupuesto'!$A$3:$A$13,$A13,'01_Presupuesto'!$Q$3:$Q$13) -> 1520000 | E13: =SUMIF('01_Presupuesto'!$A$3:$A$13,$A13,'01_Presupuesto'!$R$3:$R$13) -> 1520000 | F13: =SUMIF('01_Presupuesto'!$A$3:$A$13,$A13,'01_Presupuesto'!$S$3:$S$13) -> 1520000 | G13: =SUMIF('01_Presupuesto'!$A$3:$A$13,$A13,'01_Presupuesto'!$T$3:$T$13) -> 1520000 | H13: =SUMIF('01_Presupuesto'!$A$3:$A$13,$A13,'01_Presupuesto'!$U$3:$U$13) -> 1520000 | I13: =SUMIF('01_Presupuesto'!$A$3:$A$13,$A13,'01_Presupuesto'!$V$3:$V$13) -> 1520000 | J13: =SUMIF('01_Presupuesto'!$A$3:$A$13,$A13,'01_Presupuesto'!$W$3:$W$13) -> 1520000 | K13: =SUMIF('01_Presupuesto'!$A$3:$A$13,$A13,'01_Presupuesto'!$X$3:$X$13) -> 1520000 | L13: =SUMIF('01_Presupuesto'!$A$3:$A$13,$A13,'01_Presupuesto'!$Y$3:$Y$13) -> 1520000 | M13: =SUMIF('01_Presupuesto'!$A$3:$A$13,$A13,'01_Presupuesto'!$Z$3:$Z$13) -> 1520000 | N13: =SUM(B13:M13) -> 18240000
A14: TOTAL | B14: =SUM(B4:B13) -> 52820000 | C14: =SUM(C4:C13) -> 43320000 | D14: =SUM(D4:D13) -> 41040000 | E14: =SUM(E4:E13) -> 41040000 | F14: =SUM(F4:F13) -> 41040000 | G14: =SUM(G4:G13) -> 41040000 | H14: =SUM(H4:H13) -> 41040000 | I14: =SUM(I4:I13) -> 41040000 | ... M14: =SUM(M4:M13) -> 41040000 | N14: =SUM(B14:M14) -> 506540000

Sheet 03_Instrucciones
A1: Cómo usar esta plantilla
A3: 1) En '00_Supuestos' ajusta TRM USD/COP.
A4: 2) En '01_Presupuesto' llena en azul: Qty por mes, Costo unitario, Moneda, Mes inicio y Mes fin.
A5: 3) El modelo calcula automáticamente los montos por mes (en COP) y el total anual.
A6: 4) Revisa '02_Resumen' para ver totales por rubro y el total general.
A7: Tip: Para costos 'one-off' pon Mes inicio = Mes fin (mismo mes). Para costos recurrentes, define el rango de meses.
